cog_datasets/__init__.py
cog_datasets/_version.py
cog_datasets/download_utils.py
cog_datasets/toydata.py
cog_datasets-0.2.0.dist-info/METADATA
cog_datasets-0.2.0.dist-info/WHEEL
cog_datasets-0.2.0.dist-info/top_level.txt
cog_datasets-0.2.0.dist-info/RECORD
