Metadata-Version: 2.1
Name: cog-datasets
Version: 0.2.0
Summary: Save machine learning data sets to a common location.
Home-page: https://github.com/rsokl/cog_datasets
Author: Ryan Soklaski
Author-email: rsoklaski@gmail.com
License: MIT
Download-URL: https://github.com/rsokl/cog_datasets/tarball/v0.2.0
Platform: UNKNOWN
Requires-Python: >=3.7
Requires-Dist: numpy (>=1.19)
Requires-Dist: matplotlib (>=3.0.0)
